{
  "version": "0.28.0",
  "description": "An example transaction insights Snap.",
  "proposedName": "Transaction Insights Example Snap",
  "repository": {
    "type": "git",
    "url": "https://github.com/MetaMask/snaps-monorepo.git"
  },
  "source": {
    "shasum": "2OoGZ9leZ3NcU+fRBiJhlUWW0gIYJTAYCHEZzn30qKk=",
    "location": {
      "npm": {
        "filePath": "dist/bundle.js",
        "packageName": "transaction-insights-snap",
        "registry": "https://registry.npmjs.org/"
      }
    }
  },
  "initialPermissions": {
    "endowment:transaction-insight": {},
    "endowment:network-access": {}
  },
  "manifestVersion": "0.1"
}
