{
  "version": "0.18.1",
  "description": "An example Snap that performs IPFS operations.",
  "proposedName": "ipfs-snap",
  "repository": {
    "type": "git",
    "url": "https://github.com/MetaMask/snaps-skunkworks.git"
  },
  "source": {
    "shasum": "MGLY4zBBz0sNrnVoaQ9CTZ440IfyDxl7MG+aSP+f4hQ=",
    "location": {
      "npm": {
        "filePath": "dist/bundle.js",
        "packageName": "ipfs-snap",
        "registry": "https://registry.npmjs.org"
      }
    }
  },
  "initialPermissions": {
    "endowment:network-access": {}
  },
  "manifestVersion": "0.1"
}
