{
  "version": "2.2.3",
  "description": "MetaMask example snap demonstrating the use of the Transaction Insights API.",
  "proposedName": "Insights Example Snap",
  "repository": {
    "type": "git",
    "url": "https://github.com/MetaMask/snaps.git"
  },
  "source": {
    "shasum": "7bsB6l4qPdrB12apSpFqD0i4DNZ65OOrgvyqu0dj0Mc=",
    "location": {
      "npm": {
        "filePath": "dist/bundle.js",
        "packageName": "@metamask/insights-example-snap",
        "registry": "https://registry.npmjs.org/"
      }
    }
  },
  "initialPermissions": {
    "endowment:transaction-insight": {}
  },
  "platformVersion": "6.21.0",
  "manifestVersion": "0.1"
}
